akutils/__api__.py
akutils/__init__.py
akutils/os.py
akutils/pandas_read_files.py
akutils/pandas_serie_cleaner.py
akutils/pandas_type_conversion.py
akutils/utils_functions.py
akutils/tests/_fixtures/sales.csv
akutils/tests/_fixtures/sales_per_month/Sales_03.txt
akutils/tests/_fixtures/sales_per_month/sales_01.csv
akutils/tests/_fixtures/sales_per_month/sales_01.xlsx
akutils/tests/_fixtures/sales_per_month/sales_02.CSV
akutils/tests/_fixtures/sales_per_month/sales_02.xls
akutils/tests/_fixtures/sales_per_month/sales_03.xlsb
akutils/tests/_fixtures/sales_per_month/sales_04.xlsm
akutils/tests/unit/test_pandas_columns_to_float.py
akutils/tests/unit/test_pandas_read_files.py
akutils/tests/unit/test_pandas_serie_cleaner.py
akutils/tests/unit/test_utils_funtions.py
akutils-1.0.2.dist-info/LICENSE
akutils-1.0.2.dist-info/METADATA
akutils-1.0.2.dist-info/WHEEL
akutils-1.0.2.dist-info/top_level.txt
akutils-1.0.2.dist-info/RECORD
