Metadata-Version: 2.1
Name: akutils
Version: 1.0.2
Summary: A utility library providing generic methods for performing recurrent data manipulation in Pandas and Python.
Author-email: Alex0x4b <alex0x4b.git.su1b4@slmail.me>
Project-URL: Homepage, https://github.com/Alex0x4b/akutils
Requires-Python: <3.11,>=3.10
License-File: LICENSE
Requires-Dist: pandas >=2.2
Requires-Dist: pyarrow >=14.0.0
Requires-Dist: xlrd >=2.0.1
Requires-Dist: openpyxl >=3.1.0
Requires-Dist: pyxlsb >=1.0.10
Requires-Dist: numpy >=1.26.0
Requires-Dist: universal-pathlib ==0.1.4
Requires-Dist: PyYAML >=6.0
Requires-Dist: flake8 >=5.0.4
Requires-Dist: pytest >=7.2.2
Requires-Dist: pytest-cov >=4.0.0
Requires-Dist: mypy >=1.9.0
Requires-Dist: pandas-stubs >=2.2.0.24
Requires-Dist: types-setuptools >=69.2.0.20240317
